{
  "index.ts": "export * from './public_api';",
  "public_api.ts": "export * from './src/main';",
  "tsconfig-esm2015.json": "{\n  \"compilerOptions\": {\n    \"declaration\": true,\n    \"module\": \"es2015\",\n    \"target\": \"es2015\",\n    \"baseUrl\": \".\",\n    \"sourceMap\": false,\n    \"stripInternal\": true,\n    \"emitDecoratorMetadata\": true,\n    \"experimentalDecorators\": true,\n    \"moduleResolution\": \"node\",\n    \"outDir\": \"./esm2015\",\n    \"rootDir\": \".\",\n    \"lib\": [\"es2015\", \"dom\"],\n    \"skipLibCheck\": true,\n    \"types\": []\n  },\n  \"angularCompilerOptions\": {\n    \"annotateForClosureCompiler\": true,\n    \"strictMetadataEmit\": true,\n    \"skipTemplateCodegen\": true,\n    \"flatModuleOutFile\": \"package-name-js\",\n    \"flatModuleId\": \"package-name\"\n  },\n  \"files\": [\n    \"./public_api.ts\"\n  ]\n}",
  "tsconfig-esm5.json": "{\n  \"compilerOptions\": {\n    \"declaration\": true,\n    \"module\": \"es2015\",\n    \"target\": \"es5\",\n    \"baseUrl\": \".\",\n    \"sourceMap\": false,\n    \"stripInternal\": true,\n    \"emitDecoratorMetadata\": true,\n    \"experimentalDecorators\": true,\n    \"moduleResolution\": \"node\",\n    \"outDir\": \"./esm5\",\n    \"rootDir\": \".\",\n    \"lib\": [\"es2015\", \"dom\"],\n    \"skipLibCheck\": true,\n    \"types\": []\n  },\n  \"angularCompilerOptions\": {\n    \"annotateForClosureCompiler\": true,\n    \"strictMetadataEmit\": true,\n    \"skipTemplateCodegen\": true,\n    \"flatModuleOutFile\": \"package-name-js\",\n    \"flatModuleId\": \"package-name\"\n  },\n  \"files\": [\n    \"./public_api.ts\"\n  ]\n}"
}